neuraltrust/__init__.py
neuraltrust/api_keys/__init__.py
neuraltrust/api_keys/neuraltrust_api_key.py
neuraltrust/api_keys/openai_api_key.py
neuraltrust/base_evaluator.py
neuraltrust/cli/__init__.py
neuraltrust/cli/cli.py
neuraltrust/client/README.md
neuraltrust/client/__init__.py
neuraltrust/client/client.py
neuraltrust/client/core/__init__.py
neuraltrust/client/core/api_error.py
neuraltrust/client/core/client_wrapper.py
neuraltrust/client/core/datetime_utils.py
neuraltrust/client/core/file.py
neuraltrust/client/core/http_client.py
neuraltrust/client/core/jsonable_encoder.py
neuraltrust/client/core/pydantic_utilities.py
neuraltrust/client/core/query_encoder.py
neuraltrust/client/core/remove_none_from_dict.py
neuraltrust/client/core/request_options.py
neuraltrust/client/environment.py
neuraltrust/client/errors/__init__.py
neuraltrust/client/errors/method_not_allowed_error.py
neuraltrust/client/reference.md
neuraltrust/client/tests/utils/test_http_client.py
neuraltrust/client/tests/utils/test_query_encoding.py
neuraltrust/client/types/__init__.py
neuraltrust/client/types/metadata.py
neuraltrust/client/types/metadata_browser.py
neuraltrust/client/types/metadata_device.py
neuraltrust/client/types/metadata_os.py
neuraltrust/client/types/trace_response.py
neuraltrust/client/types/trace_task.py
neuraltrust/client/types/user.py
neuraltrust/errors/__init__.py
neuraltrust/errors/exceptions.py
neuraltrust/eval_type.py
neuraltrust/evaluation_set.py
neuraltrust/evaluator.py
neuraltrust/examples/example_sdk.py
neuraltrust/fern/fern.config.json
neuraltrust/fern/generators.yml
neuraltrust/fern/openapi/openapi.yml
neuraltrust/generate_testset.py
neuraltrust/generators/__init__.py
neuraltrust/generators/base.py
neuraltrust/generators/base_knowledge_base.py
neuraltrust/generators/knowledge_base.py
neuraltrust/generators/knowledge_vector_base.py
neuraltrust/generators/question_generators/__init__.py
neuraltrust/generators/question_generators/base.py
neuraltrust_sdk-0.2.25.dist-info/METADATA
neuraltrust_sdk-0.2.25.dist-info/WHEEL
neuraltrust_sdk-0.2.25.dist-info/entry_points.txt
neuraltrust_sdk-0.2.25.dist-info/RECORD
