Metadata-Version: 2.1
Name: neuraltrust-sdk
Version: 0.2.25
Summary: Python SDK to configure and run evaluations for your LLM-based application
Author: NeuralTrust
Author-email: support@neuraltrust.ai
Requires-Python: >=3.10,<3.13
Classifier: Programming Language :: Python :: 3
Classifier: Programming Language :: Python :: 3.10
Classifier: Programming Language :: Python :: 3.11
Classifier: Programming Language :: Python :: 3.12
Requires-Dist: PyPDF2 (>=3.0.1)
Requires-Dist: azure-search-documents (>=11.5.1)
Requires-Dist: bokeh (>=3.3.4)
Requires-Dist: colorlog (>=6.7.0,<7.0.0)
Requires-Dist: croniter (>=3.0.3)
Requires-Dist: datasets (>=2.16.0,<3.0.0)
Requires-Dist: faiss-cpu (>=1.7.4,<1.8.0.post1)
Requires-Dist: huggingface_hub (==0.23.5)
Requires-Dist: jinja2 (>=3.1.4,<4.0.0)
Requires-Dist: jsonpath_ng (>=1.6.1)
Requires-Dist: langchain (>=0.2.14)
Requires-Dist: langchain-openai (>=0.1.21)
Requires-Dist: langdetect (>=1.0.9)
Requires-Dist: openai (>=1.3.4,<2.0.0)
Requires-Dist: pandas
Requires-Dist: pydantic (>=2.7.4,<3.0.0)
Requires-Dist: pydantic-settings (>=2.2.1,<3.0.0)
Requires-Dist: pydantic_core (>=2.16.3,<3.0.0)
Requires-Dist: pyjwt (>=2.8.0)
Requires-Dist: python-dotenv (>=1.0.0,<2.0.0)
Requires-Dist: pyyaml (>=6.0.1,<7.0.0)
Requires-Dist: ragas (>=0.1.15)
Requires-Dist: requests (>=2.31.0,<3.0.0)
Requires-Dist: retrying (>=1.3.4,<2.0.0)
Requires-Dist: scipy (>=1.7.3,<1.12.0)
Requires-Dist: setfit (>=1.0.3)
Requires-Dist: sseclient-py (>=0.0.22)
Requires-Dist: tabulate (>=0.9.0)
Requires-Dist: tokenizers (>=0.19,<0.20)
Requires-Dist: torch (>=2.2.1)
Requires-Dist: umap-learn (>=0.5.6)
